lightdash/__init__.py
lightdash/main.py
lightdash/assets/bg.png
lightdash/assets/bgo.png
lightdash/assets/bgo.webm
lightdash/assets/image.png
lightdash/assets/bg_frames/frame_0001.png
lightdash/assets/bg_frames/frame_0002.png
lightdash/assets/bg_frames/frame_0003.png
lightdash/assets/bg_frames/frame_0004.png
lightdash/assets/bg_frames/frame_0005.png
lightdash/assets/bg_frames/frame_0006.png
lightdash/assets/bg_frames/frame_0007.png
lightdash/assets/bg_frames/frame_0008.png
lightdash/assets/bg_frames/frame_0009.png
lightdash/assets/bg_frames/frame_0010.png
lightdash/assets/bg_frames/frame_0011.png
lightdash/assets/bg_frames/frame_0012.png
lightdash/assets/bg_frames/frame_0013.png
lightdash/assets/bg_frames/frame_0014.png
lightdash/assets/bg_frames/frame_0015.png
lightdash/assets/bg_frames/frame_0016.png
lightdash/assets/bg_frames/frame_0017.png
lightdash/assets/bg_frames/frame_0018.png
lightdash/assets/bg_frames/frame_0019.png
lightdash/assets/bg_frames/frame_0020.png
lightdash/assets/bg_frames/frame_0021.png
lightdash/assets/bg_frames/frame_0022.png
lightdash/assets/bg_frames/frame_0023.png
lightdash/assets/bg_frames/frame_0024.png
lightdash/assets/bg_frames/frame_0025.png
lightdash/assets/bg_frames/frame_0026.png
lightdash/assets/bg_frames/frame_0027.png
lightdash/assets/bg_frames/frame_0028.png
lightdash/assets/bg_frames/frame_0029.png
lightdash/assets/bg_frames/frame_0030.png
lightdash/assets/bg_frames/frame_0031.png
lightdash/assets/bg_frames/frame_0032.png
lightdash/assets/bg_frames/frame_0033.png
lightdash/assets/bg_frames/frame_0034.png
lightdash/assets/bg_frames/frame_0035.png
lightdash/assets/bg_frames/frame_0036.png
lightdash/assets/bg_frames/frame_0037.png
lightdash/assets/bg_frames/frame_0038.png
lightdash/assets/bg_frames/frame_0039.png
lightdash/assets/bg_frames/frame_0040.png
lightdash/assets/bg_frames/frame_0041.png
lightdash/assets/bg_frames/frame_0042.png
lightdash/assets/bg_frames/frame_0043.png
lightdash/assets/bg_frames/frame_0044.png
lightdash_game-0.1.4.dist-info/METADATA
lightdash_game-0.1.4.dist-info/WHEEL
lightdash_game-0.1.4.dist-info/entry_points.txt
lightdash_game-0.1.4.dist-info/top_level.txt
lightdash_game-0.1.4.dist-info/RECORD
