Metadata-Version: 2.4
Name: lightdash-game
Version: 0.1.4
Summary: A minimalist rhythm-based runner game built with Pygame
Author-email: Priyanshu Raj <prmahatha@gmail.com>
Requires-Python: >=3.8
Requires-Dist: pygame
